climafeis/__init__.py
climafeis/climascraper.py
climafeis-1.0.10.dist-info/entry_points.txt
climafeis-1.0.10.dist-info/LICENSE
climafeis-1.0.10.dist-info/METADATA
climafeis-1.0.10.dist-info/WHEEL
climafeis-1.0.10.dist-info/RECORD
