Metadata-Version: 2.1
Name: climafeis
Version: 1.0.10
Summary: Scrape daily climate data from Canal CLIMA
Home-page: https://github.com/joaofauvel/climafeis
License: GPL-3.0-or-later
Keywords: scraping,climate,eto,evapotranspiration,dataset
Author: João Fauvel
Author-email: jmmfauvel@gmail.com
Requires-Python: >=3.8
Classifier: License :: OSI Approved :: GNU General Public License v3 or later (GPLv3+)
Classifier: Programming Language :: Python :: 3
Classifier: Programming Language :: Python :: 3.8
Classifier: Programming Language :: Python :: 3.9
Classifier: Programming Language :: Python :: 3.10
Classifier: Programming Language :: Python :: 3.11
Requires-Dist: beautifulsoup4 (>=4.12.2,<5.0.0)
Requires-Dist: html5lib (>=1.1,<2.0)
Requires-Dist: numpy (>=1.26.2,<2.0.0)
Requires-Dist: pandas (>=2.1.3,<3.0.0)
Requires-Dist: requests (>=2.31.0,<3.0.0)
Project-URL: Repository, https://github.com/joaofauvel/climafeis
